plothist/__init__.py
plothist/_version.py
plothist/_version.pyi
plothist/comparison.py
plothist/default_style.mplstyle
plothist/histogramming.py
plothist/plothist_style.py
plothist/plotters.py
plothist/test_helpers.py
plothist/variable_registry.py
plothist/examples/README.rst
plothist/examples/1d_hist/1d_comparison_asymmetry.py
plothist/examples/1d_hist/1d_comparison_difference.py
plothist/examples/1d_hist/1d_comparison_efficiency.py
plothist/examples/1d_hist/1d_comparison_only_efficiency.py
plothist/examples/1d_hist/1d_comparison_pull.py
plothist/examples/1d_hist/1d_comparison_ratio.py
plothist/examples/1d_hist/1d_comparison_relative_difference.py
plothist/examples/1d_hist/1d_comparison_split_ratio.py
plothist/examples/1d_hist/1d_elt1.py
plothist/examples/1d_hist/1d_elt1_stacked.py
plothist/examples/1d_hist/1d_elt2.py
plothist/examples/1d_hist/1d_hist_simple.py
plothist/examples/1d_hist/1d_int_category.py
plothist/examples/1d_hist/1d_profile.py
plothist/examples/1d_hist/1d_side_by_side.py
plothist/examples/1d_hist/1d_str_category.py
plothist/examples/1d_hist/README.rst
plothist/examples/2d_hist/2d_hist_correlations.py
plothist/examples/2d_hist/2d_hist_simple.py
plothist/examples/2d_hist/2d_hist_simple_discrete_colormap.py
plothist/examples/2d_hist/2d_hist_uneven.py
plothist/examples/2d_hist/2d_hist_with_projections.py
plothist/examples/2d_hist/README.rst
plothist/examples/advanced/1d_comparison_advanced.py
plothist/examples/advanced/1d_side_by_side_with_numbers.py
plothist/examples/advanced/README.rst
plothist/examples/advanced/asymmetry_comparison_advanced.py
plothist/examples/advanced/model_examples_flatten2D.py
plothist/examples/func_1d/README.rst
plothist/examples/func_1d/fct_1d.py
plothist/examples/func_1d/fct_1d_stacked.py
plothist/examples/model_ex/README.rst
plothist/examples/model_ex/model_all_comparisons.py
plothist/examples/model_ex/model_all_comparisons_no_model_unc.py
plothist/examples/model_ex/model_examples_pull.py
plothist-1.8.0.dist-info/METADATA
plothist-1.8.0.dist-info/WHEEL
plothist-1.8.0.dist-info/licenses/AUTHORS.md
plothist-1.8.0.dist-info/licenses/LICENSE
plothist-1.8.0.dist-info/RECORD
