Metadata-Version: 2.4
Name: plothist
Version: 1.8.0
Summary: Plot histograms in a scalable way and a beautiful style.
Project-URL: Homepage, https://github.com/cyrraz/plothist
Project-URL: Documentation, https://plothist.readthedocs.io/
Project-URL: Bug Tracker, https://github.com/cyrraz/plothist/issues
Author-email: Cyrille Praz <cyrraz.code@protonmail.com>, Tristan Fillinger <tristan.github@gmail.com>
License-File: AUTHORS.md
License-File: LICENSE
Classifier: Intended Audience :: Developers
Classifier: Intended Audience :: Education
Classifier: Intended Audience :: Science/Research
Classifier: License :: OSI Approved :: BSD License
Classifier: Operating System :: OS Independent
Classifier: Programming Language :: Python
Classifier: Programming Language :: Python :: 3
Classifier: Programming Language :: Python :: 3.10
Classifier: Programming Language :: Python :: 3.11
Classifier: Programming Language :: Python :: 3.12
Classifier: Programming Language :: Python :: 3.13
Classifier: Programming Language :: Python :: 3.14
Classifier: Topic :: Scientific/Engineering
Requires-Python: >=3.10
Requires-Dist: boost-histogram>=1.4.0
Requires-Dist: matplotlib>=3.10.8
Requires-Dist: numpy>=1.14.5
Requires-Dist: plothist-utils>=0.0.1
Requires-Dist: pyyaml>=6.0.3
Requires-Dist: scipy>=1.6.0
